cffm/__init__.py
cffm/click.py
cffm/config.py
cffm/field.py
cffm/multi.py
cffm/node.py
cffm/source.py
cffm/utils.py
cffm-0.2.6.dist-info/LICENSE.txt
cffm-0.2.6.dist-info/METADATA
cffm-0.2.6.dist-info/WHEEL
cffm-0.2.6.dist-info/top_level.txt
cffm-0.2.6.dist-info/RECORD
