Metadata-Version: 2.1
Name: cffm
Version: 0.2.6
Summary: Configuration of Many Sources
Home-page: https://github.com/grgi/cffm
Author: Gregor Giesen
Author-email: gregor@giesen.net
License: LGPL-3.0-or-later
Project-URL: Source, https://github.com/grgi/cffm
Project-URL: Changelog, https://github.com/grgi/cffm/blob/main/CHANGELOG.rst
Platform: any
Classifier: Development Status :: 4 - Beta
Classifier: License :: OSI Approved :: GNU Lesser General Public License v3 or later (LGPLv3+)
Classifier: Programming Language :: Python
Requires-Python: >=3.10
License-File: LICENSE.txt
Provides-Extra: click
Requires-Dist: click ; extra == 'click'
Provides-Extra: node
Requires-Dist: anytree ; extra == 'node'
Provides-Extra: testing
Requires-Dist: setuptools ; extra == 'testing'
Requires-Dist: pytest ; extra == 'testing'
Requires-Dist: pytest-cov ; extra == 'testing'
